<?xml version="1.0"?>
<annotation>
    <filename>84.tif</filename>
    <source>
        <annotation>ESRI ArcGIS Pro</annotation>
    </source>
    <size>
        <width>1024</width>
        <height>1024</height>
        <depth>3</depth>
    </size>
    <object>
        <name>1</name>
        <bndbox>
            <xmin>924.54</xmin>
            <ymin>671.04</ymin>
            <xmax>1024.00</xmax>
            <ymax>814.38</ymax>
        </bndbox>
    </object>
    <object>
        <name>1</name>
        <bndbox>
            <xmin>888.24</xmin>
            <ymin>702.83</ymin>
            <xmax>975.69</xmax>
            <ymax>838.88</ymax>
        </bndbox>
    </object>
    <object>
        <name>1</name>
        <bndbox>
            <xmin>778.20</xmin>
            <ymin>758.87</ymin>
            <xmax>859.46</xmax>
            <ymax>873.52</ymax>
        </bndbox>
    </object>
    <object>
        <name>1</name>
        <bndbox>
            <xmin>851.70</xmin>
            <ymin>726.11</ymin>
            <xmax>939.27</xmax>
            <ymax>851.44</ymax>
        </bndbox>
    </object>
    <object>
        <name>1</name>
        <bndbox>
            <xmin>811.67</xmin>
            <ymin>741.37</ymin>
            <xmax>910.75</xmax>
            <ymax>875.71</ymax>
        </bndbox>
    </object>
    <object>
        <name>1</name>
        <bndbox>
            <xmin>719.09</xmin>
            <ymin>772.30</ymin>
            <xmax>819.17</xmax>
            <ymax>896.32</ymax>
        </bndbox>
    </object>
    <object>
        <name>1</name>
        <bndbox>
            <xmin>25.62</xmin>
            <ymin>503.54</ymin>
            <xmax>165.56</xmax>
            <ymax>587.11</ymax>
        </bndbox>
    </object>
    <object>
        <name>1</name>
        <bndbox>
            <xmin>156.14</xmin>
            <ymin>483.99</ymin>
            <xmax>274.23</xmax>
            <ymax>555.62</ymax>
        </bndbox>
    </object>
</annotation>
